{"type":"PR","pr":{"number":1,"head":"5b710249a3e5657c9dbb1cc423401c5d87a9a8f9"},"user":"Rychillie Umpierre de Oliveira","status":"pending_publish","branch":"cms/posts/2016-12-06-adeus-facebook","collection":"posts","commitMessage":"Update posts “2016-12-06-adeus-facebook”","title":"Adeus Facebook","description":"Não estou feliz no facebook então quitei!","objects":{"entry":{"path":"content/blog/2016-12-06-adeus-facebook.md","sha":"fbbd1e5072ef427b27d3666a1d7522d3458a7967"},"files":[]},"timeStamp":"2020-01-02T12:10:32.273Z","version":"1"}